fn_ont_swaps_validation/__init__.py
fn_ont_swaps_validation/exceptions.py
fn_ont_swaps_validation/old_to_new.py
fn_ont_swaps_validation-0.5.dist-info/LICENSE.txt
fn_ont_swaps_validation-0.5.dist-info/METADATA
fn_ont_swaps_validation-0.5.dist-info/WHEEL
fn_ont_swaps_validation-0.5.dist-info/top_level.txt
fn_ont_swaps_validation-0.5.dist-info/RECORD
