Metadata-Version: 2.1
Name: fn-ont-swaps-validation
Version: 0.5
Summary: FN ONT swap service validations for ONTs
Home-page: https://gitlab.com/horsebridge/fn_ont_swaps_validation.git
Author: Nitin Sidhu
Author-email: nitin.sidhu23@gmail.com
License: MIT
Platform: UNKNOWN
Classifier: License :: OSI Approved :: MIT License
Classifier: Operating System :: OS Independent
Classifier: Programming Language :: Python :: 3.6
Classifier: Programming Language :: Python :: 3.7
Classifier: Programming Language :: Python :: 3.8
Requires-Python: ~=3.7
Requires-Dist: sqlalchemy
Requires-Dist: fibrenest-db-models
Requires-Dist: hns-console-logging
